blankimage_pil/__init__.py
blankimage_pil/cli.py
blankimage_pil/format_data.py
blankimage_pil/generate.py
blankimage_pil-0.1.1.dist-info/METADATA
blankimage_pil-0.1.1.dist-info/WHEEL
blankimage_pil-0.1.1.dist-info/entry_points.txt
blankimage_pil-0.1.1.dist-info/RECORD
