Metadata-Version: 2.1
Name: blankimage-pil
Version: 0.1.1
Summary: Python Command Line Tool to Generate Blank Images using Pillow
Home-page: https://pypi.org/project/blankimage-pil/
Author: Sumanth
Author-email: sumanthreddystar@gmail.com
Maintainer: Sumanth
Maintainer-email: sumanthreddystar@gmail.com
Requires-Python: >=3.8,<4.0
Classifier: Programming Language :: Python :: 3
Classifier: Programming Language :: Python :: 3.8
Classifier: Programming Language :: Python :: 3.9
Classifier: Programming Language :: Python :: 3.10
Classifier: Programming Language :: Python :: 3.11
Requires-Dist: pillow (>=10.0.1,<11.0.0)
Project-URL: Documentation, https://insumanth.github.io/blankimage-pil-docs
Project-URL: Repository, https://github.com/insumanth/blankimage-pil
